#### 目录介绍
- 01.Synchronize介绍
    - 1.1 为什么有这个
    - 1.2 Synchronize是什么
    - 1.3 它的作用是什么
- 02.Synchronize用法
    - 2.1 用在那些场景
    - 2.2 修饰代码块
    - 2.3 修饰普通方法
    - 2.4 修饰静态方法
- 03.Synchronize案例
    - 3.1 同步代码块synchronized (this)
    - 3.2 同步方法synchronized
    - 3.3 synchronized对象锁
    - 3.4 普通方法和静态方法区别
- 04.理解Synchronize锁机制
    - 4.1 锁机制原理介绍
    - 4.2 反编译查看代码
- 05.Synchronize三要素
    - 5.1 synchronized与可见性
    - 5.2 synchronized与有序性
- 06.synchronized与锁优化



### 01.Synchronize介绍
#### 1.1 为什么有这个


#### 1.2 Synchronize是什么
- `synchronized`关键字
    - 在需要原子性、可见性和有序性这三种特性的时候都可以作为其中一种解决方案，看起来是“万能”的。的确，大部分并发控制操作都能使用synchronized来完成。
    - 对于程序员来说，`synchronized`只是个关键字而已，用起来很简单。之所以我们可以在处理多线程问题时可以不用考虑太多，就是因为这个关键字帮我们屏蔽了很多细节。


#### 1.3 它的作用是什么
- synchronized实现同步的基础
    - Java中每个对象都可以作为锁。当线程试图访问同步代码时，必须先获得**对象锁**，退出或抛出异常时必须释放锁。





### 02.Synchronize用法
#### 2.1 用在那些场景
- 1.修饰一个代码块
    - 被修饰的代码块称为同步语句块，其作用的范围是大括号{}括起来的代码，作用的对象是调用这个代码块的对象；
- 2.修饰一个方法
    - 被修饰的方法称为同步方法，其作用的范围是整个方法，作用的对象是调用这个方法的对象；
- 3.修改一个静态的方法
    - 其作用的范围是整个静态方法，作用的对象是这个类的所有对象；
- 4.修饰一个类
    - 其作用的范围是synchronized后面括号括起来的部分，作用主的对象是这个类的所有对象。



#### 2.2 修饰代码块
- 修饰一个方法或者一个代码块的时候，能够保证在同一时刻最多只有一个线程执行该段代码。
    ``` 
    //同步代码块上
    public void test() {
         synchronized(this) {
              System.out.println("===");
         }
  
         synchronized(Test.class) {
              System.out.println("===");
         }

        synchronized(obj) {
            System.out.println("===");
        }
    }
    ``` 
- 第一种，synchronized(this)
    - 锁住的是该对象，类的其中一个实例，当该对象(仅仅是这一个对象)在不同线程中执行这个同步方法时，线程之间会形成互斥。达到同步效果，但如果不同线程同时对该类的不同对象执行这个同步方法时，则线程之间不会形成互斥，因为他们拥有的是不同的锁。
- 第二种，synchronized(Test.class)
    - 锁住的是该类，当所有该类的对象(多个对象)在不同线程中调用这个时，线程之间会形成互斥，达到同步效果。
- 第三种，synchronized(obj)
    - 这里面的obj可以是一个任何Object对象或数组，并不一定是它本身对象或者类，谁拥有obj这个锁，谁就能够操作该块程序代码。
- synchronized(this)和synchronized(object)区别
    * 其实并没有很大的区别，synchronized(object)本身就包含synchronized(this)这种情况，使用的场景都是对一个代码块进行加锁，效率比直接在方法名上加synchronized高一些，唯一的区别就是对象的不同。



#### 2.3 修饰普通方法
- 修饰一个方法或者一个代码块的时候，能够保证在同一时刻最多只有一个线程执行该段代码。
    ``` java
    //同步的方法
    pubilc synchronized void test() {
    
    }
    ``` 
- 锁住的是该对象，类的其中一个实例，当该对象(仅仅是这一个对象)在不同线程中执行这个同步方法时，线程之间会形成互斥。达到同步效果，但如果不同线程同时对该类的不同对象执行这个同步方法时，则线程之间不会形成互斥，因为他们拥有的是不同的锁。


#### 2.4 修饰静态方法
- 修饰静态方法如下所示
    ``` java
    //同步的方法
    pubilc synchronized static void test() {
    
    }
    ``` 
- 锁住的是该类，当所有该类的对象(多个对象)在不同线程中调用这个static同步方法时，线程之间会形成互斥，达到同步效果。







### 03.Synchronize案例
#### 3.1 同步代码块synchronized (this)
- 简单使用
    ``` 
    Thread01 t01 = new Thread01();
    System.out.println("synchronized 关键字使用 \n" +"--------------------------");
    Thread ta = new Thread(t01,"A");
    Thread tb = new Thread(t01,"B");
    ta.start();
    tb.start();
    
    private class Thread01 implements Runnable{
        @Override
        public void run() {
            synchronized (this) {
                for(int i=0;i<3;i++){
                    System.out.println(Thread.currentThread().getName()+" synchronized loop "+i);
                }
            }
        }
    }
    
    执行结果：
    synchronized 关键字使用
    --------------------------
    B synchronized loop 0
    B synchronized loop 1
    B synchronized loop 2
    A synchronized loop 0
    A synchronized loop 1
    A synchronized loop 2
    ``` 


#### 3.2 同步方法synchronized
- 同步代码块
    ``` 
    System.out.println("synchronized 关键字使用 \n" +"--------------------------");
    Thread t02A = new Thread(new Runnable() {
        @Override
        public void run() {
            method01();
        }
    },"A");
    Thread t02B = new Thread(new Runnable() {
    
        @Override
        public void run() {
            method02();
        }
    },"B");
    Thread t02C = new Thread(new Runnable() {
        @Override
        public void run() {
            method3();
        }
    },"C");
    t02A.start();
    t02B.start();
    t02C.start();
    
    
    public void method01(){
        synchronized (this) {
            int i=0;
            while(i++ < 3){
                System.out.println(Thread.currentThread().getName() +":"+ i);
                try {
                    Thread.sleep(1000);
                } catch (InterruptedException e) {
                    e.printStackTrace();
                }
            }
        }
    }
    
    public void method02(){
        //第2种方式:当一个线程访问object的一个synchronized(this)同步代码块时，
        //其他线程对object中所有其它synchronized(this)同步代码块的访问将被阻塞。
        synchronized (this) {
            int j=0;
            while(j++ < 3){
                System.out.println(Thread.currentThread().getName() +":"+ j);
                try {
                    Thread.sleep(1000);
                } catch (InterruptedException e) {
                    e.printStackTrace();
                }
            }
        }
    }
    
    /*
     * 当一个线程访问object的一个synchronized(this)同步代码块时，
     * 它就获得了这个object的对象锁。
     * 结果，其它线程对该object对象所有同步代码部分的访问都被暂时阻塞。
     */
    public synchronized void method3(){
        int k=0;
        while(k++ < 3){
            System.out.println(Thread.currentThread().getName() +":"+ k);
            try {
                Thread.sleep(1000);
            } catch (InterruptedException e) {
                e.printStackTrace();
            }
        }
    }
    
    执行结果：
    synchronized 关键字使用
    --------------------------
    B:1
    B:2
    B:3
    C:1
    C:2
    C:3
    A:1
    A:2
    A:3
    ``` 


#### 3.3 synchronized对象锁
- synchronized对象锁
    ``` 
    final InnerObject innerObj = new InnerObject();
    System.out.println("synchronized 关键字使用 \n" +"--------------------------");
    Thread t03A = new Thread(new Runnable() {
        @Override
        public void run() {
            outerMethod01(innerObj);
        }
    },"A");
    Thread t03B = new Thread(new Runnable() {
        @Override
        public void run() {
            outerMethod02(innerObj);
        }
    },"B");
    t03A.start();
    t03B.start();
    
    class InnerObject{
        private void innerMethod01(){
            int i=0;
            while(i++ < 3){
                System.out.println(Thread.currentThread().getName() +":"+ i);
                try {
                    Thread.sleep(1000);
                } catch (InterruptedException e) {
                    e.printStackTrace();
                }
            }
        }
    
        private void innerMethod02(){
            int j=0;
            while(j++ < 3){
                System.out.println(Thread.currentThread().getName() +":"+ j);
                try {
                    Thread.sleep(1000);
                } catch (InterruptedException e) {
                    e.printStackTrace();
                }
            }
        }
    }
    
    /**
     * 外部类方法1
     */
    private void outerMethod01(InnerObject innerObj){
        synchronized (innerObj) {
            innerObj.innerMethod01();
        }
    }
    
    /**
     * 外部类方法2
     */
    private void outerMethod02(InnerObject innerObj){
        innerObj.innerMethod02();
    }
    
    执行结果：
    synchronized 关键字使用
    --------------------------
    A:1
    B:1
    B:2
    A:2
    B:3
    A:3
    ``` 


#### 3.4 普通方法和静态方法区别
- 测试代码如下所示
    ```
    private void test() {
        final TestSynchronized test1 = new TestSynchronized();
        final TestSynchronized test2 = new TestSynchronized();
        Thread t1 = new Thread(new Runnable() {
    
            @Override
            public void run() {
                test1.method01("a");
                //test1.method02("a");
            }
        });
        Thread t2 = new Thread(new Runnable() {
    
            @Override
            public void run() {
                test2.method01("b");
                //test2.method02("a");
            }
        });
        t1.start();
        t2.start();
    }
    
    private static class TestSynchronized{
        private int num1;
        public synchronized void method01(String arg) {
            try {
                if("a".equals(arg)){
                    num1 = 100;
                    System.out.println("tag a set number over");
                    Thread.sleep(1000);
                }else{
                    num1 = 200;
                    System.out.println("tag b set number over");
                }
                System.out.println("tag = "+ arg + ";num ="+ num1);
            } catch (InterruptedException e) {
                e.printStackTrace();
            }
        }
    
        private static int  num2;
        public static synchronized void method02(String arg) {
            try {
                if("a".equals(arg)){
                    num2 = 100;
                    System.out.println("tag a set number over");
                    Thread.sleep(1000);
                }else{
                    num2 = 200;
                    System.out.println("tag b set number over");
                }
                System.out.println("tag = "+ arg + ";num ="+ num2);
            } catch (InterruptedException e) {
                e.printStackTrace();
            }
        }
    }
    
    //调用method01方法打印日志【普通方法】
    tag a set number over
    tag b set number over
    tag = b;num =200
    tag = a;num =100
    
    
    //调用method02方法打印日志【static静态方法】
    tag a set number over
    tag = a;num =100
    tag b set number over
    tag = b;num =200
    ```
- 在static方法前加synchronized：静态方法属于类方法，它属于这个类，获取到的锁，是属于类的锁。
- 在普通方法前加synchronized：非static方法获取到的锁，是属于当前对象的锁。 
- 结论：类锁和对象锁不同，synchronized修饰不加static的方法，锁是加在单个对象上，不同的对象没有竞争关系；修饰加了static的方法，锁是加载类上，这个类所有的对象竞争一把锁。





### 04.理解Synchronize锁机制
#### 4.1 锁机制原理介绍
- Synchronized进过编译，会在同步块的前后分别形成monitorenter和monitorexit这个两个字节码指令。
    - 在执行monitorenter指令时，首先要尝试获取对象锁。如果这个对象没被锁定，或者当前线程已经拥有了那个对象锁，把锁的计算器加1，相应的，在执行monitorexit指令时会将锁计算器就减1，当计算器为0时，锁就被释放了。如果获取对象锁失败，那当前线程就要阻塞，直到对象锁被另一个线程释放为止。
- JVM基于进入和退出`Monitor`对象来实现 **代码块同步** 和 **方法同步** ，两者实现细节不同。
    - **代码块同步：** 在编译后通过将`monitorenter`指令插入到同步代码块的开始处，将`monitorexit`指令插入到方法结束处和异常处，通过反编译字节码可以观察到。任何一个对象都有一个`monitor`与之关联，线程执行`monitorenter`指令时，会尝试获取对象对应的`monitor`的所有权，即尝试获得对象的锁。
    - **方法同步：** synchronized方法在`method_info结构`有`ACC_synchronized`标记，线程执行时会识别该标记，获取对应的锁，实现方法同步。
- 方法级的同步是隐式的。
    - 同步方法的常量池中会有一个`ACC_SYNCHRONIZED`标志。当某个线程要访问某个方法的时候，会检查是否有`ACC_SYNCHRONIZED`，如果有设置，则需要先获得监视器锁，然后开始执行方法，方法执行之后再释放监视器锁。这时如果其他线程来请求执行方法，会因为无法获得监视器锁而被阻断住。
    - 值得注意的是，如果在方法执行过程中，发生了异常，并且方法内部并没有处理该异常，那么在异常被抛到方法外面之前监视器锁会被自动释放。
- 同步代码块使用`monitorenter`和`monitorexit`两个指令实现。
    - 可以把执行`monitorenter`指令理解为加锁，执行`monitorexit`理解为释放锁。
    - 每个对象维护着一个记录着被锁次数的计数器。未被锁定的对象的该计数器为0，当一个线程获得锁（执行`monitorenter`）后，该计数器自增变为1，当同一个线程再次获得该对象的锁的时候，计数器再次自增。当同一个线程释放锁（执行`monitorexit`指令）的时候，计数器再自减。当计数器为0的时候。锁将被释放，其他线程便可以获得锁。
- 无论是`ACC_SYNCHRONIZED`还是`monitorenter`、`monitorexit`都是基于Monitor实现的
    - 在Java虚拟机(HotSpot)中，Monitor是基于C++实现的，由ObjectMonitor实现。
    - ObjectMonitor类中提供了几个方法，如`enter`、`exit`、`wait`、`notify`、`notifyAll`等。`sychronized`加锁的时候，会调用objectMonitor的enter方法，解锁的时候会调用exit方法。
    - **任意一个对象都拥有自己的监视器**，当同步代码块或同步方法时，执行方法的线程必须先获得该对象的监视器才能进入同步块或同步方法，没有获取到监视器的线程将会被阻塞，并进入同步队列，状态变为`BLOCKED`。当成功获取监视器的线程释放了锁后，会唤醒阻塞在同步队列的线程，使其重新尝试对监视器的获取。



#### 4.2 反编译查看代码
- `synchronized`，是Java中用于解决并发情况下数据同步访问的一个很重要的关键字。
    - 当我们想要保证一个共享资源在同一时间只会被一个线程访问到时，我们可以在代码中使用`synchronized`关键字对类或者对象加锁。
- 对上面的代码进行反编译，可以得到如下代码：
    ```
    public synchronized void doSth();
        descriptor: ()V
        flags: ACC_PUBLIC, ACC_SYNCHRONIZED
        Code:
          stack=2, locals=1, args_size=1
             0: getstatic     #2                  // Field java/lang/System.out:Ljava/io/PrintStream;
             3: ldc           #3                  // String Hello World
             5: invokevirtual #4                  // Method java/io/PrintStream.println:(Ljava/lang/String;)V
             8: return
    
    public void doSth1();
        descriptor: ()V
        flags: ACC_PUBLIC
        Code:
          stack=2, locals=3, args_size=1
             0: ldc           #5                  // class com/hollis/SynchronizedTest
             2: dup
             3: astore_1
             4: monitorenter
             5: getstatic     #2                  // Field java/lang/System.out:Ljava/io/PrintStream;
             8: ldc           #3                  // String Hello World
            10: invokevirtual #4                  // Method java/io/PrintStream.println:(Ljava/lang/String;)V
            13: aload_1
            14: monitorexit
            15: goto          23
            18: astore_2
            19: aload_1
            20: monitorexit
            21: aload_2
            22: athrow
            23: return
    ```
- 通过反编译后代码可以看出：
    - 对于同步方法，JVM采用`ACC_SYNCHRONIZED`标记符来实现同步。 
    - 对于同步代码块，JVM采用`monitorenter`、`monitorexit`两个指令来实现同步。




### 08.synchronized与原子性
- 原子性是指一个操作是不可中断的，要全部执行完成，要不就都不执行。
    - 线程是CPU调度的基本单位。
        - CPU有时间片的概念，会根据不同的调度算法进行线程调度。当一个线程获得时间片之后开始执行，在时间片耗尽之后，就会失去CPU使用权。所以在多线程场景下，由于时间片在线程间轮换，就会发生原子性问题。
- 在Java中，为了保证原子性，提供了两个高级的字节码指令`monitorenter`和`monitorexit`。
    - 前面中，介绍过，这两个字节码指令，在Java中对应的关键字就是`synchronized`。
    - 通过`monitorenter`和`monitorexit`指令，可以保证被`synchronized`修饰的代码在同一时间只能被一个线程访问，在锁未释放之前，无法被其他线程访问到。因此，在Java中可以使用`synchronized`来保证方法和代码块内的操作是原子性的。
- 多线程保证了原子性
    - 线程1在执行`monitorenter`指令的时候，会对Monitor进行加锁，加锁后其他线程无法获得锁，除非线程1主动解锁。即使在执行过程中，由于某种原因，比如CPU时间片用完，线程1放弃了CPU，但是，他并没有进行解锁。而由于`synchronized`的锁是可重入的，下一个时间片还是只能被他自己获取到，还是会继续执行代码。直到所有代码执行完。这就保证了原子性。




### 05.Synchronize三要素
### 5.1 synchronized与可见性
- 可见性是指当多个线程访问同一个变量时，一个线程修改了这个变量的值，其他线程能够立即看得到修改的值。
- Java内存模型规定了所有的变量都存储在主内存中，每条线程还有自己的工作内存，线程的工作内存中保存了该线程中是用到的变量的主内存副本拷贝，线程对变量的所有操作都必须在工作内存中进行，而不能直接读写主内存。不同的线程之间也无法直接访问对方工作内存中的变量，线程间变量的传递均需要自己的工作内存和主存之间进行数据同步进行。所以，就可能出现线程1改了某个变量的值，但是线程2不可见的情况。
- 前面我们介绍过，被`synchronized`修饰的代码，在开始执行时会加锁，执行完成后会进行解锁。而为了保证可见性，有一条规则是这样的：对一个变量解锁之前，必须先把此变量同步回主存中。这样解锁后，后续线程就可以访问到被修改后的值。
- 所以，synchronized关键字锁住的对象，其值是具有可见性的。



#### 5.2 synchronized与有序性
- 有序性即程序执行的顺序按照代码的先后顺序执行。
    - 除了引入了时间片以外，由于处理器优化和指令重排等，CPU还可能对输入代码进行乱序执行，比如load->add->save 有可能被优化成load->save->add 。这就是可能存在有序性问题。
    - 这里需要注意的是，`synchronized`是无法禁止指令重排和处理器优化的。也就是说，`synchronized`无法避免上述提到的问题。
- 那么，为什么还说`synchronized`也提供了有序性保证呢？
    - 这就要再把有序性的概念扩展一下了。Java程序中天然的有序性可以总结为一句话：如果在本线程内观察，所有操作都是天然有序的。如果在一个线程中观察另一个线程，所有操作都是无序的。
- 以上这句话也是《深入理解Java虚拟机》中的原句



### 06.synchronized与锁优化
- 前面介绍了`synchronized`的用法、原理以及对并发编程的作用。是一个很好用的关键字。
- `synchronized`其实是借助Monitor实现的，在加锁时会调用objectMonitor的`enter`方法，解锁的时候会调用`exit`方法。
- 事实上，只有在JDK1.6之前，synchronized的实现才会直接调用ObjectMonitor的`enter`和`exit`，这种锁被称之为重量级锁。
- 所以，在JDK1.6中出现对锁进行了很多的优化，进而出现轻量级锁，偏向锁，锁消除，适应性自旋锁，锁粗化(自旋锁在1.4就有，只不过默认的是关闭的，jdk1.6是默认开启的)，这些操作都是为了在线程之间更高效的共享数据 ，解决竞争问题。






### 其他介绍
#### 01.关于博客汇总链接
- 1.[技术博客汇总](https://www.jianshu.com/p/614cb839182c)
- 2.[开源项目汇总](https://blog.csdn.net/m0_37700275/article/details/80863574)
- 3.[生活博客汇总](https://blog.csdn.net/m0_37700275/article/details/79832978)
- 4.[喜马拉雅音频汇总](https://www.jianshu.com/p/f665de16d1eb)
- 5.[其他汇总](https://www.jianshu.com/p/53017c3fc75d)



#### 02.关于我的博客
- github：https://github.com/yangchong211
- 知乎：https://www.zhihu.com/people/yczbj/activities
- 简书：http://www.jianshu.com/u/b7b2c6ed9284
- csdn：http://my.csdn.net/m0_37700275
- 喜马拉雅听书：http://www.ximalaya.com/zhubo/71989305/
- 开源中国：https://my.oschina.net/zbj1618/blog
- 泡在网上的日子：http://www.jcodecraeer.com/member/content_list.php?channelid=1
- 邮箱：yangchong211@163.com
- 阿里云博客：https://yq.aliyun.com/users/article?spm=5176.100- 239.headeruserinfo.3.dT4bcV
- segmentfault头条：https://segmentfault.com/u/xiangjianyu/articles
- 掘金：https://juejin.im/user/5939433efe88c2006afa0c6e


