#### 目录介绍
- 01.基本类型有哪些
    - 1.1 8种类型说明
    - 1.2 8种类型格式
- 02.字面值有哪些类型
    - 2.1 字面值分类
    - 2.2 为何有字面值
- 03.整型介绍
    - 3.1 整型数据
    - 3.2 整数字面值
- 04.浮点型介绍
    - 4.1 浮点型数据
    - 4.2 浮点数字面值
- 05.字符介绍
    - 5.1 字符型数据
    - 5.2 字符字面值
- 06.布尔介绍
    - 6.1 布尔数据
    - 6.2 布尔字面值
- 07.基本类型转换
    - 7.1 加宽转换
    - 7.2 收窄转换
    - 7.3 表达式中的自动类型提升
- 08.基本数据存储位置
    - 8.1 先看个问题
    - 8.2 局部变量存储位置
    - 8.3 成员变量存储位置
    - 8.4 静态变量存储位置
    - 8.5 举例说明




### 01.基本类型有哪些
#### 1.1 8种类型
- Java定义了八种基本数据类型：
    - **byte，short，int，long，char，float，double，boolean**。
- 基本数据类型也称为简单类型，这些类型可以分为四组：
    - 1.整型。包括byte，short，int，long。用于表示有符号整数。
    - 2.浮点型。包括float，double。用于表示带小数位的数字。
    - 3.字符型。包括char。用于表示字符集中的符号。
    - 4.布尔型。包括boolean。用于表示true/false值。
    - 开发者可以直接使用这些类型，也可以使用它们来构造数组以及自定义类型。因此，它们形成了所有可以创建的其他类型的基础。Java在其他方面是完全面向对象的，但基本数据类型并不是面向对象的，这样设计的原因是为了效率。将基本数据类型设计为对象会极大地降低性能。
    - 因为Java语言的特色之一就是具备可移植性，即不管在哪个平台下运行，一份代码无需修改就可以直接运行。为了确保这一点，基本数据类型被定义为具有明确的范围和数学行为，与C和C++这类语言“允许整数的大小随着执行环境的要求而变化”不同，Java语言的数据类型都具有严格定义的范围。无论在那种平台下，int总是32位的。虽然严格指定基本数据类型的范围在某些环境下会造成性能损失，但这是为了实现可移植性而必须付出的。


#### 1.2 8种类型格式
- Java的八种基本类型说明如下所示，其中每一种都有特定的格式和大小
    |基本类型|说明|字节数
    |:----:|:----:|:----:
    |byte|字节长度的整数，八位|1个字节
    |short|短整数，十六位|2个字节
    |int|整数，三十二位|4个字节
    |long|长整数，六十四位|8个字节
    |float|单精度浮点数，三十二位|4个字节
    |double|双精度浮点数，六十四位|8个字节
    |char|Unicode字符|2个字节
    |boolean|布尔值|1个字节
- 声明为byte、char、short类型的数据是否也能够存储超出它们的取值范围的数值呢？
    - 答案是肯定的。而且这些超出取值范围的数值也会带来一些麻烦。比如说，声明为char类型的变量局部变量实际上可能为负数。
    - 当然，在正常使用Java编译器的情况下，生成给的字节码会遵守Java虚拟机规范对编译器的约束，因此你无须过分担心局部变量会超出它们的取值范围。
- Java的浮点类型采用IEEE 754浮点数格式。
    - 以float为例，浮点类型通常有2个0，+0.0F以及-0.0F。
    - 前者在Java里是0，后者是符号位为1、其它位为0的浮点数，在内存中等同于十六进制整数0x80000000(即-0.0F 可通过 Float,intBitsToFloat(0x80000000)求得)。尽管它们的内存数值不同，但是在Java中+0.0F == -0.0F会返回真。
    - 在有了+0.0F和-0.0F这两个定义后，我们便可以定义浮点数中的正无穷及负无穷。正无穷就是任意正浮点数（不包括+0.0F）除以+0.0F得到的值，而负无穷是任意正浮点数除以-0.0F得到的值。在Java中，正无穷和负无穷是有确切的值，在内存中分别等同于十六进制整数0x7F800000 和 0xFF800000。
    - 而[0x7F800001, 0x7FFFFFFF] 和 [0xFF800001, 0xFFFFFFFF] 对应的都是NaN(Not-a-Number)。当然，一般我们计算得出的NaN，比如说通过+0.0F/+0.0F,在内存中应为0x7FC00000。这个数字，我们都称之为标准的NaN，而其他的我们称之为不标准的NaN。
- NaN有一个有趣的特性：除了"!="始终返回true之外，所有其它比较结果都会返回false。举例来说，
    - NaN < 1.0F -> false
    - NaN >= 1.0F -> false
    - f != NaN -> true (f为任意浮点数)
    - f == NaN -> false (f为任意浮点数)
    - 因此，我们在程序里做浮点数比较时，需要考虑上述特性。



### 02.字面值有哪些类型
#### 2.1 字面值分类
- 基本类型的字面值有四种子类型：
    - 整数字面值，浮点数字面值，字符字面值，布尔字面值


#### 2.2 为何有字面值


### 03.整型数据介绍
#### 3.1 整型数据
- Java定义了四种整数类型：byte，short，int，long。
    - 所有这些类型都是有符号的、正的整数或者负的整数。Java不支持无符号（正值）的整数。
    名称|宽度|范围
    :--:|:--:|:--:|
    long|64|-9 223 372 036 854 775 808 ~ 9 223 372 036 854 775 807
    int|32|-2 147 483 648 ~ 2 147 483 647
    short|16|-32 768 ~ 32767
    byte|8|-128 ~ 127
- 当中，最常用的整数类型是int。
    - int类型经常用于控制循环变量和索引数组。对于那些不需要更大范围的int类型数值的情况，你可能会认为使用范围更小的byte和short类型效率会更高，然而事实并非如此。因为在表达式中使用byte和short值时，当对表达式求值时它们会被提升为int类型。所以，当需要使用整数时，int通常是最好的选择。



#### 3.2 整数字面值
- 整数字面值可以写为十进制，十六进制（加前缀0x或0X），八进制（加前缀0），二进制（加前缀0B或0b）
    ```
    //十进制
    int x=10;
    //十六进制数，即十进制的32
    int y=0x20;
    //八进制，即十进制的15
    int z=017;
    //二进制，即十进制的7
    int u=0b0111;
    ```
- 整数字面值用于将值赋给byte，short，int和long类型的变量。所赋值不能超出变量的存储范围
    - 例如，以下代码在IDE中就会提示错误，因为byte的最大值为127
    ```
    byte b = 250;
    ```
    - 要将一个值赋给long类型时，在数字的后面要加上后缀字母L或l。否则，如下代码中的整数值其实是被看做是int类型的
    ```
    long a = 120;
    ```
    - 在以下代码中，就会产生一个错误，因为99999999999超出了int类型的存储能力。为了解决这个问题，需要在数字后加上后缀字母L或l
    ```
    long a = 99999999999;
    ```
- 如果整数字面值太长，可读性会受到影响。
    - 从Java 7开始，可用在整数字面值中使用下划线将数字分隔开。
    ```
    //十进制
    int x=1_000_000;
    //十六进制数，即十进制的32
    int y=0x2_0;
    //八进制，即十进制的15
    int z=0_17;
    //二进制，即十进制的7
    int u=0b0_111;
    ```



### 04.浮点型介绍
#### 4.1 浮点型数据
- 浮点数也称为实数，当计算需要小数精度的表达式时使用。
    名称|宽度|范围
    :--:|:--:|:--:|
    float|32|1.4e-045 ~ 3.4e+038
    double|64|4.9e-324 ~ 1.8e+308
- **float**
    - float类型表示使用32位存储的单精度数值。在某些处理器上，单精度运行速度更快，并且占用的空间是双精度的一半，但是当数值非常大或者非常小时会变得不精确。
    - 如果需要小数部分，且精确度要求不高时，就可以考虑使用float类型。
- **double**
    - double类型表示使用64位存储的双精度数值。在sin()、cos()和sqrt()这类数学函数中，返回值都是double类型。
    - 如果需要在很多次迭代运算中保持精度，或是操作非常大的数值时，double类型是最佳选择。


#### 4.2 浮点数字面值
- 浮点数包含以下四个部分
    - 一个整数部分
    - 一个小数点
    - 一个小数部分
    - 一个可选的指数
- 例如，在1.7e8中，1是整数部分，7是小数部分，8是指数
    - 在float和double类型中，0的整数部分是可选的
    - 例如，**0.5**可以写成**.5**
    - 浮点数字面值加上的后缀字母F或f表明其为float类型，如果没有标明，该浮点数字面值将是double类型




### 05.字符介绍
#### 5.1 字符型数据
- char是用于存储字符的数据类型。
    - Java的设计初衷是允许程序员编写在世界范围内均可使用的语言，因此采用了Unicode标准来表示字符。Unicode定义了一个完全国际化的字符集，能够表示全部人类语言中的所有字符，为此需要使用十六位宽度来存储。char的范围是0 ~ 65536，没有负的char值。
- 对于一些语种，例如英语、德语等，可以使用八位宽度来表示这类语言的字符，使用Unicode在一定程度上会降低效率，但这是为了在全球获得可移植性而必须付出的代价。
- 尽管char被设计为容纳Unicode字符，但也可以用作整数类型，可以对char类型的变量执行算术运算。



#### 5.2 字符字面值
- 字符字面值是一个Unicode字符，或者是单引号括起来的一个转义序列
    - 例如
    ```
    'a'
    'b'
    '\b' 回退字符
    '\n' 换行
    '\r' 回车
    ```

### 06.布尔介绍
#### 6.1 布尔数据
- 在Java语言规范中，boolean类型的值只有两种可能，它们分别用true和false来表示，显然这两种符号是不能被虚拟机直接使用的。
- 在Java虚拟机规范中，boolean类型则被映射成int类型。具体来说，就是
    - true -> 1
    - false -> 0
    - 这个编码规则约束了Java字节码的具体实现。
- 举个例子，对于存储boolean数组的字节码，Java虚拟机需保证直接存入的值是1或0.
    - Java虚拟机规范同时要求Java编译器遵守这个编码规则，并且用整数相关的字节码来实现逻辑运算，以基于boolean类型条件的跳转。这样一来，编译而成的class文件，除了字段和传入参数外，基本看不出boolean类型的痕迹了。
- 如何使用命令行看字节码
    - 首先使用命令行输入：javac Xx.java。然后会编译出一个后缀名为.class的文件。
    - 接着通过javap查看字节码，这里输入命令：javap -c Xx。
- 看一下编译后字节码代码
    ``` java
    Compiled from "Test2.java"
    public class day1.Test2 {
      public day1.Test2();
        Code:
           0: aload_0
           1: invokespecial #1                  // Method java/lang/Object."<init>":()V
           4: return
    
      public static void main(java.lang.String[]);
        Code:
           0: iconst_1
           1: istore_1
           2: iload_1
           3: ifeq          14
           6: getstatic     #2                  // Field java/lang/System.out:Ljava/io/PrintStream;
           9: ldc           #3                  // String  吃了
          11: invokevirtual #4                  // Method java/io/PrintStream.println:(Ljava/lang/String;)V
          14: iconst_1
          15: iload_1
          16: if_icmpne     27
          19: getstatic     #2                  // Field java/lang/System.out:Ljava/io/PrintStream;
          22: ldc           #5                  // String  真吃了
          24: invokevirtual #4                  // Method java/io/PrintStream.println:(Ljava/lang/String;)V
          27: return
    }
    ```
- 可以看到，Java编译器的确遵守了相同的编码规则。
    - 当然，这个约束很容易绕开。除了Asmtools以外，我们还有很过可以修改Java字节码的库，比如ASM等。
    - 对于Java虚拟机来说，它所看到的boolean类型早就被映射为整数类型。因此，将原本声明为boolean类型的局部变量，赋值成为除了0、1之外的变量，在Java虚拟机看来是合法的。


#### 6.2 布尔字面值
- 布尔类型有两个值，分别为true和false。
    - 例如，声明一个布尔变量bool
    ```
    boolean bool=true;
    ```


### 07.基本类型转换
- 在涉及处理不同数据类型时，常常需要将一个变量的值赋给另一个变量，这就需要进行类型转换
- 默认转换
	* 1：byte,short,char—int—long—float—double
	* 2：byte,short,char相互之间补转换，他们参与运算首先转换为int类型
- 强制转换
	* 格式: 目标类型 变量名 = (目标类型)值或变量名
	* int a = (int) 15.7f;
- 注意要点
    ``` java
    !!!!!!!注意!!!!!!!!
    1:在java中，任何一个整数默认为 int 类型 (1)
    2:在java种，任何一个小数，默认为 double 类型( 1.0)
    3:123L 或者 123l 编译器会将该数当成long类型
    4:12.345f 或者12.345F 编译器会将该数当成float类型
    ```


#### 7.1 加宽转换
- 当从一种基本类型转换向另一种基本类型时，如果后者的大小和前者相同或者更大，就叫做加宽转换
    - 例如，将int（32位）转为long（64位）。此时不会有信息丢失的风险，且加宽转换是隐式发生的，不需要在代码中任何事情
    - 例如
    ``` java
    int a=10;
    long b=a;
    ```

#### 7.2 收窄转换
- 收窄转换发生在从一种基本类型转换为另一种更小类型的转换中
    - 例如，从long（64位）到int（32位）。收窄转换需要显示调用，用圆括号指定目标类型
    ``` java
    long a=10;
    int b=(int)a;
    ```
    - 如果被转换的值比目标类型的容量还要大的话，收窄转换将导致信息丢失
    - 例如，9876543210对int类型来说太大了
    ``` java
    long a=9876543210L;
    int b=(int)a;
    //输出值是1286608618
    System.out.println(b);
    ```


#### 7.3 表达式中的自动类型提升
- 除了赋值外，在表达式中也可能会发生类型转换。在表达式中，中间值要求的精度有时会超出操作数的范围。
    - 例如：
    ``` java
    byte a = 40;
    byte b = 50;
    byte c = 100;
    int d = a * b / c;
    ```
    - 中间部分 a \* b 很容易超出byte操作数的范围。为了解决这类问题，当对表达式求值时，Java会自动将每个byte，short或char操作数提升为int类型。这意味着使用int类型而不是byte类型执行子表达式a \* b。因此，即时a和b都被指定为byte类型，中间表达式（50 * 40）的结果2000是合法的。
- 自动类型提升很有用，但有时候会导致难以理解的编译时错误。例如：
    ``` java
    byte b=10;
    //错误
    b= b*2;
    ```
    - 如上代码试图将 10 * 2 的结果（一个完全有效的byte值）保存到byte变量中，但是编译器却提示错误。当计算表达式的值时，操作数被自动提升为int类型，所以结果也被提升为int类型。因此，现在是试图将一个int类型值转为byte变量，如果不使用强制类型转换，就不能将结果赋给byte变量。
- Java定义了几个应用于表达式的类型提升规则。
    - 1.对于一元操作符来说，如果操作数的类型是byte，short或char，运算结果提升为int类型
    - 2.对与二元操作符来说，提升规则是从以下几条依次选择一条执行
    - 如果操作数类型均为byte、short或char，那么两个数均转为int类型，结果数也将为int类型
    - 如果操作数包含double类型，那么另一个操作数也转为double，结果数也将为double类型
    - 如果操作数包含float类型，那么另一个操作数也转为float，结果数也将为float类型
    - 如果操作数包含long类型，那么另一个操作数也转为long，结果数也将为long类型






### 08.基本数据存储位置
#### 8.1 先看个问题
- 先看一个题目
    - Java中的基本数据类型一定存储在栈中吗？
- 答案说明
    - 首先说明，"java中的基本数据类型一定存储在栈中的吗？”这句话肯定是错误的。
    - 基本数据类型是放在栈中还是放在堆中，这取决于基本类型在何处声明，下面对数据类型在内存中的存储问题来解释一下。


#### 8.2 局部变量存储位置
- 在方法中声明的变量，即该变量是局部变量
    - 每当程序调用方法时，系统都会为该方法建立一个方法栈，其所在方法中声明的变量就放在方法栈中，当方法结束系统会释放方法栈，其对应在该方法中声明的变量随着栈的销毁而结束，这就局部变量只能在方法中有效的原因。
    - 在方法中声明的变量可以是基本类型的变量，也可以是引用类型的变量。
    - 当声明是基本类型的变量的时，其变量名及值（变量名及值是两个概念）是放在JAVA虚拟机栈中
    - 当声明的是引用变量时，所声明的变量（该变量实际上是在方法中存储的是内存地址值）是放在JAVA虚拟机的栈中，该变量所指向的对象是放在堆类存中的


#### 8.3 成员变量存储位置
- 在类中声明的变量是成员变量，也叫全局变量
    - 放在堆中的（因为全局变量不会随着某个方法执行结束而销毁）。
    - 同样在类中声明的变量即可是基本类型的变量，也可是引用类型的变量。
    - 当声明的是基本类型的变量其变量名及其值放在堆内存中的
    - 引用类型时，其声明的变量仍然会存储一个内存地址值，该内存地址值指向所引用的对象。引用变量名和对应的对象仍然存储在相应的堆中


#### 8.4 静态变量存储位置
- 静态变量其实就是常量
    - 注意是：存储在JVM的方法区中
    - static变量在类加载时被初始化，存储在JVM的方法区中，整个内存中只有一个static变量的拷贝，可以使用类名直接访问，也可以通过类的实例化对象访问，一般不推荐通过实例化对象访问，通俗的讲static变量属于类，不属于对象，任何实例化的对象访问的都是同一个static变量，任何地放都可以通过类名来访问static变量。


#### 8.5 举例说明
- 此外，为了反驳观点" Java的基本数据类型都是存储在栈的 "，我们也可以随便举出一个反例，例如：
    ```
    int[] array=new int[]{1,2};
    ```
    - 由于new了一个对象，所以new int[]{1,2}这个对象时存储在堆中的，也就是说1,2这两个基本数据类型是存储在堆中，这也就很有效的反驳了基本数据类型一定是存储在栈中~~



### 10.Java基本类型的大小
- **Java虚拟机每调用一个方法，变回创建一个栈帧**。
    - 为了方便理解，这里我只讨论供解释器使用的解释栈帧(interpreted frame)。
    - 这种栈帧有两个主要的组成部分，分别是局部变量区，以及字节码的操作数栈。这里的局部变量是广义的，除了普遍意义下的局部变量之外，它还包含实例方法的"this指针"以及方法所接受的参数。
    - 在Java虚拟机规范中，局部变量区等价于一个数组，并且可以用正整数来索引。除了long、double值需要用两个赎罪单元来存储外，其它基本类型以及引用类型的值均占用一个数组单元。
    - 也就是说，boolean、byte、char、short这四种类型，在栈上占用的空间和int是一样的，和引用类型是一样的。因此，在32位的HotSpot中，这些类型在栈上将占用4个字节；而64位的HotSpot中，他们将占用8个字节。
    - 当然，这种情况仅存在于局部变量，而并不会出现在存储于堆中的字段或者数组元素上。对于byte、char以及short这三种类型的字段或者数组单元，它们在堆上占用的空间分别为一字节、两字节以及两字节。也就是说，跟这些类型的值域想吻合，因此，当我们将一个Int类型的值，存储到这些类型的字段或者数组时，相当于做了一次隐式的掩码操作。举例来说，当我们把0xFFFFFFFF(-1)存储到一个声明为char类型的字段里时，由于改字段仅占两个字节，所以高两位的字节便会被截取掉，最终存入"\uFFFF"。
- boolean字段和boolean数组则标胶特殊。
    - 在HotSpot中，boolean类型占用一个字节，而boolean数组则直接用byte数组来实现的。为了保证堆的boolean类型值是合法的，HotSpot在存储时显式地进行掩码操作，也就是说，只取最后一位的值存入boolean字段或数组中。
- Java虚拟机的算数运算几乎全部依赖于操作数栈。也就是说，我们需要将堆中的boolean、byte、char以及short加载到操作数栈上，而后将栈上的值当成int类型来运算。
    - 对于boolean、char这两个无符号类型来说，加载时伴随着零扩展。举个例子，char的大小是两个字节。在加载时char的值会被复制到int类型的低二字节，而高二字节则会用0来填充。
    - 对于byte、short这两个类型来说，加载伴随着符号扩展。举个例子，short的大小是两个字节。在加载时short的值同样会被复制到int类型的低二字节。如果该short值为非负数，即最高位为0，那么该int类型的值的高二字节会用0来填充，否则会用1来填充。



### 11.通过实践查看栈桢
- 将boolean类型的值存入字段中时,Java虚拟机所做的掩码操作。撰写Java代码：
    ``` java
    public class Foo{
    	static boolean boolValue;//这里不在栈区
    	public static void main(String[] args){
    		boolValue = true;
    		if(boolValue)
    			System.out.println("Hello Java!");
    		if(boolValue == true)
    			System.out.println("Hello JVM!");
    	}
    }
    ```
- 使用javac编译并用java运行它
    ``` java
    javac Foo.java
    java Foo
    Hello Java!
    Hello JVM!
    ```
- 使用asmtools.jar来反汇编class文件
    - java -cp ./asmtools.jar org.openjdk.asmtools.jdis.Main Foo.class > Foo.jasm.1
    - 得到Foo.jasm.1文件
    ``` java
    super public class Foo
    	version 52:0
    {
     
    static Field boolValue:Z;
     
    public Method "<init>":"()V"
    	stack 1 locals 1
    {
    		aload_0;
    		invokespecial	Method java/lang/Object."<init>":"()V";
    		return;
    }
     
    public static Method main:"([Ljava/lang/String;)V"
    	stack 2 locals 1
    {
    		iconst_2;//看这里
    		putstatic	Field boolValue:"Z";
    		getstatic	Field boolValue:"Z";
    		ifeq	L18;
    		getstatic	Field java/lang/System.out:"Ljava/io/PrintStream;";
    		ldc	String "Hello Java!";
    		invokevirtual	Method java/io/PrintStream.println:"(Ljava/lang/String;)V";
    	L18:	stack_frame_type same;
    		getstatic	Field boolValue:"Z";
    		iconst_1;
    		if_icmpne	L33;
    		getstatic	Field java/lang/System.out:"Ljava/io/PrintStream;";
    		ldc	String "Hello JVM!";
    		invokevirtual	Method java/io/PrintStream.println:"(Ljava/lang/String;)V";
    	L33:	stack_frame_type same;
    		return;
    }
     
    } // end Class Foo
    ```
- 再运行指令(其作用为将Foo.jasm.1文件中第一个iconst_1 替换为iconst_2, 输出到文件Foo.jasm中)
    - awk 'NR==1,/iconst_1/{sub(/iconst_1/, "iconst_2")} 1' Foo.jasm.1 > Foo.jasm
    - 得到Foo.jasm文件
    ``` java
    super public class Foo
    	version 52:0
    {
     
    static Field boolValue:Z;
     
    public Method "<init>":"()V"
    	stack 1 locals 1
    {
    		aload_0;
    		invokespecial	Method java/lang/Object."<init>":"()V";
    		return;
    }
     
    public static Method main:"([Ljava/lang/String;)V"
    	stack 2 locals 1
    {
    		iconst_2;//看这里
    		putstatic	Field boolValue:"Z";
    		getstatic	Field boolValue:"Z";
    		ifeq	L18;
    		getstatic	Field java/lang/System.out:"Ljava/io/PrintStream;";
    		ldc	String "Hello Java!";
    		invokevirtual	Method java/io/PrintStream.println:"(Ljava/lang/String;)V";
    	L18:	stack_frame_type same;
    		getstatic	Field boolValue:"Z";
    		iconst_1;
    		if_icmpne	L33;
    		getstatic	Field java/lang/System.out:"Ljava/io/PrintStream;";
    		ldc	String "Hello JVM!";
    		invokevirtual	Method java/io/PrintStream.println:"(Ljava/lang/String;)V";
    	L33:	stack_frame_type same;
    		return;
    }
     
    } // end Class Foo
    ```
- 现在我们将赋给boolValue的值为2，再将其汇编如Foo.class
    - java -cp ./asmtools.jar org.openjdk.asmtools.jasm.Main Foo.jasm
    - 这时，我们再运行java Foo,发现没有任何输出。
- 我们再按照上述步骤重复一遍，只需修改指令(即修改赋给boolValue的值为3)
    - awk 'NR==1,/iconst_1/{sub(/iconst_1/, "iconst_3")} 1' Foo.jasm.1 > Foo.jasm
    - 得到新的反汇编代码
    ``` java
    super public class Foo
    	version 52:0
    {
     
    static Field boolValue:Z;
     
    public Method "<init>":"()V"
    	stack 1 locals 1
    {
    		aload_0;
    		invokespecial	Method java/lang/Object."<init>":"()V";
    		return;
    }
     
    public static Method main:"([Ljava/lang/String;)V"
    	stack 2 locals 1
    {
    		iconst_3; //看这里
    		putstatic	Field boolValue:"Z";
    		getstatic	Field boolValue:"Z";
    		ifeq	L18;
    		getstatic	Field java/lang/System.out:"Ljava/io/PrintStream;";
    		ldc	String "Hello Java!";
    		invokevirtual	Method java/io/PrintStream.println:"(Ljava/lang/String;)V";
    	L18:	stack_frame_type same;
    		getstatic	Field boolValue:"Z";
    		iconst_1;
    		if_icmpne	L33;
    		getstatic	Field java/lang/System.out:"Ljava/io/PrintStream;";
    		ldc	String "Hello JVM!";
    		invokevirtual	Method java/io/PrintStream.println:"(Ljava/lang/String;)V";
    	L33:	stack_frame_type same;
    		return;
    }
     
    } // end Class Foo
    ```
- 再反汇编运行
    ``` java
    java -cp ./asmtools.jar org.openjdk.asmtools.jasm.Main Foo.jasm
    java Foo
    Hello Java!
    Hello JVM!
    ```
    - 发现全部运行了。
- 得出结论：
    - static修饰的成员不是存在栈区，所以在进行boolean类型赋值时会进行掩码操作，即只保留最低位，2的最低位为0，3的最低位为1，所以将3赋值给静态boolean类型变量时和true(1)没有任何差别。




### 其他介绍
#### 01.关于博客汇总链接
- 1.[技术博客汇总](https://www.jianshu.com/p/614cb839182c)
- 2.[开源项目汇总](https://blog.csdn.net/m0_37700275/article/details/80863574)
- 3.[生活博客汇总](https://blog.csdn.net/m0_37700275/article/details/79832978)
- 4.[喜马拉雅音频汇总](https://www.jianshu.com/p/f665de16d1eb)
- 5.[其他汇总](https://www.jianshu.com/p/53017c3fc75d)



#### 02.关于我的博客
- github：https://github.com/yangchong211
- 知乎：https://www.zhihu.com/people/yczbj/activities
- 简书：http://www.jianshu.com/u/b7b2c6ed9284
- csdn：http://my.csdn.net/m0_37700275
- 喜马拉雅听书：http://www.ximalaya.com/zhubo/71989305/
- 开源中国：https://my.oschina.net/zbj1618/blog
- 泡在网上的日子：http://www.jcodecraeer.com/member/content_list.php?channelid=1
- 邮箱：yangchong211@163.com
- 阿里云博客：https://yq.aliyun.com/users/article?spm=5176.100- 239.headeruserinfo.3.dT4bcV
- segmentfault头条：https://segmentfault.com/u/xiangjianyu/articles
- 掘金：https://juejin.im/user/5939433efe88c2006afa0c6e







