#### 目录介绍
- 01.lazy
    - 1.1 by lazy作用
    - 1.2 lazy使用场景
    - 1.3 作用范围
- 02.lateinit
    - 1.1 使用场景
    - 1.2 注意问题
- 03.by lazy和lateinit的区别
- 04.什么时候用这个
- 05.by lazy实现过程



### 好消息
- 博客笔记大汇总【16年3月到至今】，包括Java基础及深入知识点，Android技术博客，Python学习笔记等等，还包括平时开发中遇到的bug汇总，当然也在工作之余收集了大量的面试题，长期更新维护并且修正，持续完善……开源的文件是markdown格式的！同时也开源了生活博客，从12年起，积累共计N篇[近100万字，陆续搬到网上]，转载请注明出处，谢谢！
- **链接地址：https://github.com/yangchong211/YCBlogs**
- 如果觉得好，可以star一下，谢谢！当然也欢迎提出建议或者问题，万事起于忽微，量变引起质变！



### 01.lazy
#### 1.1 by lazy作用
- 懒初始化是指推迟一个变量的初始化时机，变量在使用的时候才去实例化，这样会更加的高效。因为我们通常会遇到这样的情况，一个变量直到使用时才需要被初始化，或者仅仅是它的初始化依赖于某些无法立即获得的上下文。 



#### 1.2 lazy使用场景
- by lazy本身是一种属性委托。属性委托的关键字是by。by lazy 的写法如下：
    - 需要注意的是by lazy一般只能修饰val不变的对象，不能修饰var可变对象。
    ```
    //lazy 委托属性可以用于只读属性的惰性加载
    private val compositeDisposable: CompositeDisposable by lazy {
        CompositeDisposable()
    }
    
    //懒初始化是指推迟一个变量的初始化时机，变量在使用的时候才去实例化，这样会更加的高效。
    //因为我们通常会遇到这样的情况，一个变量直到使用时才需要被初始化，
    //或者仅仅是它的初始化依赖于某些无法立即获得的上下文。
    private val model: HomeModel by lazy {
        HomeModel()
    }
    ```

#### 1.3 作用范围
- by lazy可以使用于类属性或者局部变量。
    ```
    //用于属性延迟初始化
    val name: Int by lazy { 1 }
    
    //用于局部变量延迟初始化
    public fun foo() {
        val bar by lazy { "hello" }
        val model: HomeModel by lazy {
            HomeModel()
        }
        println("逗比------------$bar")
        println("逗比------------$model")
    }
    ```
- 以下以name属性为代表来讲解by kazy的原理，局部变量的初始化也是一样的原理。
    - by lazy要求属性声明为val，即不可变变量，在java中相当于被final修饰。这意味着该变量一旦初始化后就不允许再被修改值了(基本类型是值不能被修改，对象类型是引用不能被修改)。{}内的操作就是返回唯一一次初始化的结果。




### 02.lateinit
#### 1.1 使用场景
- 如何使用
    ```
    private lateinit var name: String               //正确的
    private lateinit var adapter : AndroidCollectAdapter        //正确的
    private lateinit var a : Int                //报错
    ```
- lateinit var只能用来修饰类属性，不能用来修饰局部变量，并且只能用来修饰对象，不能用来修饰基本类型(因为基本类型的属性在类加载后的准备阶段都会被初始化为默认值)。
- lateinit var的作用也比较简单，就是让编译期在检查时不要因为属性变量未被初始化而报错。


#### 1.2 注意问题
- Kotlin相信当开发者显式使用lateinit var 关键字的时候，他一定也会在后面某个合理的时机将该属性对象初始化的(然而，如果用完才想起还没初始化该怎么办？？？)。
- lateinit 本身的含义是延迟初始化，但是在编译时必须保证 lateinit 修饰的参数被初始化，否则编译之后运行会报错。注意是运行是会报错，这个问题很严重，所以用的话一定要记得初始化。



### 03.by lazy和lateinit的区别
- 区别如下
    - by lazy 修饰val的变量
    - lateinit 修饰var的变量，且变量是非空的类型



### 04.什么时候用这个
- Koltin中属性在声明的同时也要求要被初始化，否则会报错。 例如以下代码:
    ```
    private var name0: String //报错
    private var name1: String = "yc逗比" //不报错
    private var name2: String? = null //不报错
    ```
- 遇到问题
    - 可是有的时候，并不想声明一个类型可空的对象，而且也没办法在对象一声明的时候就为它初始化，那么这时就需要用到Kotlin提供的延迟初始化。
- Kotlin中有两种延迟初始化的方式。
    - 一种是lateinit var，一种是by lazy。



### 05.by lazy实现过程
- 首先看看kotlin代码
    ```
    class Test{
        private val name: Int by lazy { 1 }
        fun printname() {
            println(name)
        }
    }
    ```
- 在IDEA中点击toolbar中的 Tools -> Kotlin -> Show Kotlin ByteCode， 查看编辑器右侧的工具栏:
    - 注意看init方法和clinit方法中的代码
    ```
    public final class com/ycbjie/android/util/Test {
    
    
      // access flags 0x1018
      final static synthetic [Lkotlin/reflect/KProperty; $$delegatedProperties
    
      // access flags 0x8
      static <clinit>()V
        ICONST_1
        ANEWARRAY kotlin/reflect/KProperty
        DUP
        ICONST_0
        NEW kotlin/jvm/internal/PropertyReference1Impl
        DUP
        LDC Lcom/ycbjie/android/util/Test;.class
        INVOKESTATIC kotlin/jvm/internal/Reflection.getOrCreateKotlinClass (Ljava/lang/Class;)Lkotlin/reflect/KClass;
        LDC "name"
        LDC "getName()I"
        INVOKESPECIAL kotlin/jvm/internal/PropertyReference1Impl.<init> (Lkotlin/reflect/KDeclarationContainer;Ljava/lang/String;Ljava/lang/String;)V
        INVOKESTATIC kotlin/jvm/internal/Reflection.property1 (Lkotlin/jvm/internal/PropertyReference1;)Lkotlin/reflect/KProperty1;
        CHECKCAST kotlin/reflect/KProperty
        AASTORE
        PUTSTATIC com/ycbjie/android/util/Test.$$delegatedProperties : [Lkotlin/reflect/KProperty;
        RETURN
        MAXSTACK = 8
        MAXLOCALS = 0
    
      // access flags 0x12
      private final Lkotlin/Lazy; name$delegate
    
      // access flags 0x12
      private final getName()I
       L0
        ALOAD 0
        GETFIELD com/ycbjie/android/util/Test.name$delegate : Lkotlin/Lazy;
        ASTORE 1
        ALOAD 0
        ASTORE 2
        GETSTATIC com/ycbjie/android/util/Test.$$delegatedProperties : [Lkotlin/reflect/KProperty;
        ICONST_0
        AALOAD
        ASTORE 3
       L1
        ALOAD 1
        INVOKEINTERFACE kotlin/Lazy.getValue ()Ljava/lang/Object;
       L2
        CHECKCAST java/lang/Number
        INVOKEVIRTUAL java/lang/Number.intValue ()I
        IRETURN
       L3
        LOCALVARIABLE this Lcom/ycbjie/android/util/Test; L0 L3 0
        MAXSTACK = 2
        MAXLOCALS = 4
    
      // access flags 0x11
      public final printname()V
       L0
        LINENUMBER 8 L0
        ALOAD 0
        INVOKESPECIAL com/ycbjie/android/util/Test.getName ()I
        ISTORE 1
       L1
        GETSTATIC java/lang/System.out : Ljava/io/PrintStream;
        ILOAD 1
        INVOKEVIRTUAL java/io/PrintStream.println (I)V
       L2
       L3
        LINENUMBER 9 L3
        RETURN
       L4
        LOCALVARIABLE this Lcom/ycbjie/android/util/Test; L0 L4 0
        MAXSTACK = 2
        MAXLOCALS = 2
    
      // access flags 0x1
      public <init>()V
       L0
        LINENUMBER 3 L0
        ALOAD 0
        INVOKESPECIAL java/lang/Object.<init> ()V
       L1
        LINENUMBER 5 L1
        ALOAD 0
        GETSTATIC com/ycbjie/android/util/Test$name$2.INSTANCE : Lcom/ycbjie/android/util/Test$name$2;
        CHECKCAST kotlin/jvm/functions/Function0
        INVOKESTATIC kotlin/LazyKt.lazy (Lkotlin/jvm/functions/Function0;)Lkotlin/Lazy;
        PUTFIELD com/ycbjie/android/util/Test.name$delegate : Lkotlin/Lazy;
        RETURN
       L2
        LOCALVARIABLE this Lcom/ycbjie/android/util/Test; L0 L2 0
        MAXSTACK = 2
        MAXLOCALS = 1
    
      @Lkotlin/Metadata;(mv={1, 1, 13}, bv={1, 0, 3}, k=1, d1={"\u0000\u001a\n\u0002\u0018\u0002\n\u0002\u0010\u0000\n\u0002\u0008\u0002\n\u0002\u0010\u0008\n\u0002\u0008\u0005\n\u0002\u0010\u0002\n\u0000\u0018\u00002\u00020\u0001B\u0005\u00a2\u0006\u0002\u0010\u0002J\u0006\u0010\u0009\u001a\u00020\nR\u001b\u0010\u0003\u001a\u00020\u00048BX\u0082\u0084\u0002\u00a2\u0006\u000c\n\u0004\u0008\u0007\u0010\u0008\u001a\u0004\u0008\u0005\u0010\u0006\u00a8\u0006\u000b"}, d2={"Lcom/ycbjie/android/util/Test;", "", "()V", "name", "", "getName", "()I", "name$delegate", "Lkotlin/Lazy;", "printname", "", "android"})
      // access flags 0x18
      final static INNERCLASS com/ycbjie/android/util/Test$name$2 null null
      // compiled from: Test.kt
      // debug info: SMAP
    Test.kt
    Kotlin
    *S Kotlin
    *F
    + 1 Test.kt
    com/ycbjie/android/util/Test
    *L
    1#1,11:1
    *E
    
    }
    
    
    // ================com/ycbjie/android/util/Test$name$2.class =================
    // class version 50.0 (50)
    // access flags 0x30
    // signature Lkotlin/jvm/internal/Lambda;Lkotlin/jvm/functions/Function0<Ljava/lang/Integer;>;
    // declaration: com/ycbjie/android/util/Test$name$2 extends kotlin.jvm.internal.Lambda implements kotlin.jvm.functions.Function0<java.lang.Integer>
    final class com/ycbjie/android/util/Test$name$2 extends kotlin/jvm/internal/Lambda  implements kotlin/jvm/functions/Function0  {
    
    
      // access flags 0x1041
      public synthetic bridge invoke()Ljava/lang/Object;
       L0
        LINENUMBER 3 L0
        ALOAD 0
        INVOKEVIRTUAL com/ycbjie/android/util/Test$name$2.invoke ()I
        INVOKESTATIC java/lang/Integer.valueOf (I)Ljava/lang/Integer;
        ARETURN
        MAXSTACK = 1
        MAXLOCALS = 1
    
      // access flags 0x11
      public final invoke()I
       L0
        LINENUMBER 5 L0
        ICONST_1
       L1
        IRETURN
       L2
        LOCALVARIABLE this Lcom/ycbjie/android/util/Test$name$2; L0 L2 0
        MAXSTACK = 1
        MAXLOCALS = 1
    
      // access flags 0x0
      <init>()V
        ALOAD 0
        ICONST_0
        INVOKESPECIAL kotlin/jvm/internal/Lambda.<init> (I)V
        RETURN
        MAXSTACK = 2
        MAXLOCALS = 1
    
      // access flags 0x19
      public final static Lcom/ycbjie/android/util/Test$name$2; INSTANCE
    
      // access flags 0x8
      static <clinit>()V
        NEW com/ycbjie/android/util/Test$name$2
        DUP
        INVOKESPECIAL com/ycbjie/android/util/Test$name$2.<init> ()V
        PUTSTATIC com/ycbjie/android/util/Test$name$2.INSTANCE : Lcom/ycbjie/android/util/Test$name$2;
        RETURN
        MAXSTACK = 2
        MAXLOCALS = 0
    
      @Lkotlin/Metadata;(mv={1, 1, 13}, bv={1, 0, 3}, k=3, d1={"\u0000\u0008\n\u0000\n\u0002\u0010\u0008\n\u0000\u0010\u0000\u001a\u00020\u0001H\n\u00a2\u0006\u0002\u0008\u0002"}, d2={"<anonymous>", "", "invoke"})
      OUTERCLASS com/ycbjie/android/util/Test <init> ()V
      // access flags 0x18
      final static INNERCLASS com/ycbjie/android/util/Test$name$2 null null
      // compiled from: Test.kt
    }
    ```
- 该段代码是在字节码生成的public <init>()V 方法内的。
    - 之所以是在该方法内，是因为非单例object的Kotlin类的属性初始化代码语句经过编译器处理后都会被收集到该方法内，如果是object对象，对应的属性初始化代码语句则会被收集到static <clinit>()V方法中。
    - 另外，在字节码中，这两个方法是拥有不同方法签名的，这与语言级别上判断两个方法是否相同的方式有所不同。前者是实例构造方法，后者是类构造方法。
- L0与L1之间的字节码代表调用了Object()的构造方法，这是默认的父类构造方法。L2之后的是本地变量表说明。L1与L2之间的字节码对应如下kotlin代码：
    ```
    private val name: Int by lazy { 1 }
    ```
- 注意看public <init>()V方法中的代码，L1与L2之间这段字节码的意思是:
    - 源代码行号5对应字节码方法体内的行号1；
    - 将this(非静态方法默认的第一个本地变量)推送至栈顶;
    - 获取静态变量com.ycbjie.bylazy.Test$name$2.INSTANCE;
    - 检验INSTANCE能否转换为kotlin.jvm.functions.Function0类;
    - 调用静态方法kotlin.LazyKt.lazy(kotlin.jvm.functions.Function0)，将INSTANCE作为参数传入，并获得一个kotlin.Lazy类型的返回值;
    - 将以上返回值赋值给com.ycbjie.bylazy.Test.name$delegate;
    - 最后结束方法。
- 相当于Java中代码
    ```
    Test() {
        name$delegate = LazyKt.lazy((Function0)name$2.INSTANCE)
    }
    ```





### 关于其他内容介绍
#### 01.关于博客汇总链接
- 1.[技术博客汇总](https://www.jianshu.com/p/614cb839182c)
- 2.[开源项目汇总](https://blog.csdn.net/m0_37700275/article/details/80863574)
- 3.[生活博客汇总](https://blog.csdn.net/m0_37700275/article/details/79832978)
- 4.[喜马拉雅音频汇总](https://www.jianshu.com/p/f665de16d1eb)
- 5.[其他汇总](https://www.jianshu.com/p/53017c3fc75d)



#### 02.关于我的博客
- github：https://github.com/yangchong211
- 知乎：https://www.zhihu.com/people/yczbj/activities
- 简书：http://www.jianshu.com/u/b7b2c6ed9284
- csdn：http://my.csdn.net/m0_37700275
- 喜马拉雅听书：http://www.ximalaya.com/zhubo/71989305/
- 开源中国：https://my.oschina.net/zbj1618/blog
- 泡在网上的日子：http://www.jcodecraeer.com/member/content_list.php?channelid=1
- 邮箱：yangchong211@163.com
- 阿里云博客：https://yq.aliyun.com/users/article?spm=5176.100- 239.headeruserinfo.3.dT4bcV
- segmentfault头条：https://segmentfault.com/u/xiangjianyu/articles
- 掘金：https://juejin.im/user/5939433efe88c2006afa0c6e






